{
    "env_id":  9,
    "front":  [
                  {
                      "f1":  32.74,
                      "f2":  4.0
                  },
                  {
                      "f1":  32.832,
                      "f2":  4.0
                  },
                  {
                      "f1":  32.74,
                      "f2":  4.0
                  },
                  {
                      "f1":  32.74,
                      "f2":  4.0
                  }
              ],
    "instance_id":  "P12_H_01",
    "metadata":  {
                     "group":  "Large-H"
                 },
    "source":  "offline_archive_union"
}
